README.md
setup.cfg
setup.py
Marginal_Contribution_Feature_Importance.egg-info/PKG-INFO
Marginal_Contribution_Feature_Importance.egg-info/SOURCES.txt
Marginal_Contribution_Feature_Importance.egg-info/dependency_links.txt
Marginal_Contribution_Feature_Importance.egg-info/requires.txt
Marginal_Contribution_Feature_Importance.egg-info/top_level.txt
mci/__init__.py
mci/mci_values.py
mci/estimators/__init__.py
mci/estimators/base_estimator.py
mci/estimators/beam_search.py
mci/estimators/brute_force.py
mci/estimators/contribution_tracker.py
mci/estimators/permutation_samplling.py
mci/evaluators/__init__.py
mci/evaluators/evaluator_function.py
mci/evaluators/lgb_evaluator.py
mci/evaluators/sklearn_evaluator.py
mci/utils/__init__.py
mci/utils/estimators_util.py
mci/utils/multi_process_lst.py
mci/utils/pac_noise.py
mci/utils/type_hints.py