Metadata-Version: 1.1
Name: Marginal-Contribution-Feature-Importance
Version: 0.1.0
Summary: implementation of the marginal contribution feature importance score
Home-page: UNKNOWN
Author: UNKNOWN
Author-email: UNKNOWN
License: UNKNOWN
Download-URL: https://github.com/TAU-MLwell/Marginal-Contribution-Feature-Importance/archive/refs/tags/0.1.0.tar.gz
Platform: UNKNOWN
